<?xml version="1.0" encoding="UTF-8" ?>
<!DOCTYPE mapper PUBLIC "-//mybatis.org//DTD Mapper 3.0//EN"
        "http://mybatis.org/dtd/mybatis-3-mapper.dtd">
<mapper namespace="Nagasawa.valid_X.infra.mybatis.mapper.FollowMapper">

    <insert id="insert">
        INSERT INTO follows (follower_id, followee_id)
        VALUES (#{followerId}, #{followeeId})
        ON CONFLICT (follower_id, followee_id) DO NOTHING
    </insert>

    <delete id="delete">
        DELETE FROM follows
        WHERE follower_id = #{followerId}
        AND followee_id = #{followeeId}
    </delete>

    <select id="exists" resultType="boolean">
        SELECT EXISTS(
        SELECT 1 FROM follows
        WHERE follower_id = #{followerId}
        AND followee_id = #{followeeId}
        )
    </select>

    <select id="countFollowers" resultType="long">
        SELECT COUNT(*) FROM follows WHERE followee_id = #{userId}
    </select>

    <select id="countFollowing" resultType="long">
        SELECT COUNT(*) FROM follows WHERE follower_id = #{userId}
    </select>

    <!-- 自分をフォローしているユーザID一覧（新しい順、cursorId は created_at のエポックms） -->
    <select id="listFollowers" resultType="long">
        SELECT follower_id
        FROM follows
        WHERE followee_id = #{userId}
        <if test="cursorId != null">
            AND created_at &lt; to_timestamp(#{cursorId} / 1000.0)
        </if>
        ORDER BY created_at DESC
        LIMIT #{limit}
    </select>

    <!-- 自分がフォローしているユーザID一覧（新しい順） -->
    <select id="listFollowing" resultType="long">
        SELECT followee_id
        FROM follows
        WHERE follower_id = #{userId}
        <if test="cursorId != null">
            AND created_at &lt; to_timestamp(#{cursorId} / 1000.0)
        </if>
        ORDER BY created_at DESC
        LIMIT #{limit}
    </select>
</mapper>